{
	"numElements": 10,
	"elements": [
		{
			"position": [16, 16],
			"type": "portal"
		},
		{
			"position": [4, 4],
			"type": "rock_L"
		},
		{
			"position": [14, 4],
			"type": "rock_L"
		},
		{
			"position": [4, 14],
			"type": "rock_M"
		},
		{
			"position": [14, 14],
			"type": "rock_M"
		},
		{
			"position": [6, 7],
			"type": "rock_S"
		},
		{
			"position": [3, 16],
			"type": "flames1"
		},
		{
			"position": [10, 10],
			"type": "flames1"
		},
		{
			"position": [7, 6],
			"type": "flames1"
		},
		{
			"position": [4, 9],
			"type": "flames2"
		}
	]
}